django_emoticons-1.2.dist-info/DESCRIPTION.rst
django_emoticons-1.2.dist-info/METADATA
django_emoticons-1.2.dist-info/RECORD
django_emoticons-1.2.dist-info/WHEEL
django_emoticons-1.2.dist-info/metadata.json
django_emoticons-1.2.dist-info/top_level.txt
emoticons/__init__.py
emoticons/settings.py
emoticons/demo/__init__.py
emoticons/demo/demo.html
emoticons/demo/settings.py
emoticons/demo/urls.py
emoticons/static/emoticons/angel.gif
emoticons/static/emoticons/angry.gif
emoticons/static/emoticons/bandit.gif
emoticons/static/emoticons/bear.gif
emoticons/static/emoticons/beer.gif
emoticons/static/emoticons/bigsmile.gif
emoticons/static/emoticons/blush.gif
emoticons/static/emoticons/bow.gif
emoticons/static/emoticons/brokenheart.gif
emoticons/static/emoticons/bug.gif
emoticons/static/emoticons/cake.gif
emoticons/static/emoticons/call.gif
emoticons/static/emoticons/cash.gif
emoticons/static/emoticons/clapping.gif
emoticons/static/emoticons/coffee.gif
emoticons/static/emoticons/cool.gif
emoticons/static/emoticons/crying.gif
emoticons/static/emoticons/dance.gif
emoticons/static/emoticons/devil.gif
emoticons/static/emoticons/doh.gif
emoticons/static/emoticons/drink.gif
emoticons/static/emoticons/drunk.gif
emoticons/static/emoticons/dull.gif
emoticons/static/emoticons/emo.gif
emoticons/static/emoticons/envy.gif
emoticons/static/emoticons/evilgrin.gif
emoticons/static/emoticons/flower.gif
emoticons/static/emoticons/fubar.gif
emoticons/static/emoticons/giggle.gif
emoticons/static/emoticons/handshake.gif
emoticons/static/emoticons/happy.gif
emoticons/static/emoticons/headbang.gif
emoticons/static/emoticons/heart.gif
emoticons/static/emoticons/hi.gif
emoticons/static/emoticons/inlove.gif
emoticons/static/emoticons/itwasntme.gif
emoticons/static/emoticons/kiss.gif
emoticons/static/emoticons/lipssealed.gif
emoticons/static/emoticons/mail.gif
emoticons/static/emoticons/makeup.gif
emoticons/static/emoticons/middlefinger.gif
emoticons/static/emoticons/mmm.gif
emoticons/static/emoticons/mooning.gif
emoticons/static/emoticons/movie.gif
emoticons/static/emoticons/muscle.gif
emoticons/static/emoticons/music.gif
emoticons/static/emoticons/nerd.gif
emoticons/static/emoticons/ninja.gif
