Metadata-Version: 1.1
Name: django-emoticons
Version: 1.2
Summary: A usefull and incredible Django application that allow you to use emoticons in your templates :)
Home-page: https://github.com/Fantomas42/django-emoticons
Author: Fantomas42
Author-email: fantomas42@gmail.com
License: BSD License
Keywords: django,emoticons,smiley
Platform: UNKNOWN
Classifier: Framework :: Django
Classifier: Development Status :: 5 - Production/Stable
Classifier: Environment :: Web Environment
Classifier: Programming Language :: Python
Classifier: Programming Language :: Python :: 3
Classifier: Intended Audience :: Developers
Classifier: Operating System :: OS Independent
Classifier: License :: OSI Approved :: BSD License
Classifier: Topic :: Software Development :: Libraries :: Python Modules
